setup.py
toolsbi.py
toolsbi.egg-info/PKG-INFO
toolsbi.egg-info/SOURCES.txt
toolsbi.egg-info/dependency_links.txt
toolsbi.egg-info/top_level.txt