Metadata-Version: 2.1
Name: toolsbi
Version: 1.0.0
Summary: Descripción del paquete
Home-page: https://url_del_proyecto.com
Author: Matias Villalobos
Author-email: mati.v.arriagada@gmail.com
